awsme/__init__.py
awsme/async_recorder.py
awsme/awsme.py
awsme/buffered_recorder.py
awsme/cli.py
awsme/cloud_watch.py
awsme/dummy.py
awsme/factory.py
awsme/immediate_recorder.py
awsme/metric.py
awsme-1.0.0.dist-info/LICENSE
awsme-1.0.0.dist-info/METADATA
awsme-1.0.0.dist-info/WHEEL
awsme-1.0.0.dist-info/entry_points.txt
awsme-1.0.0.dist-info/top_level.txt
awsme-1.0.0.dist-info/RECORD
