Metadata-Version: 2.1
Name: awsme
Version: 1.0.0
Summary: AWS CloudWatch client library to send metrics conveniently and efficiently
Home-page: https://github.com/peterdemin/awsme
Author: Peter Demin
Author-email: peterdemin@gmail.com
License: MIT license
Keywords: awsme
Platform: UNKNOWN
Classifier: Development Status :: 5 - Production/Stable
Classifier: Intended Audience :: Developers
Classifier: License :: OSI Approved :: MIT License
Classifier: Natural Language :: English
Classifier: Programming Language :: Python :: 3
Classifier: Programming Language :: Python :: 3.6
Requires-Dist: click
Requires-Dist: attrs
Provides-Extra: boto3
Requires-Dist: boto3 ; extra == 'boto3'
